ovpn_portal/__init__.py
ovpn_portal/cli/commands/dev.py
ovpn_portal/cli/commands/serve.py
ovpn_portal/cli/commands/setup.py
ovpn_portal/cli/commands/version.py
ovpn_portal/cli/main.py
ovpn_portal/core/__init__.py
ovpn_portal/core/auth.py
ovpn_portal/core/cli.py
ovpn_portal/core/config.py
ovpn_portal/core/logging.py
ovpn_portal/core/templates/client.ovpn
ovpn_portal/core/version.py
ovpn_portal/core/vpn.py
ovpn_portal/static/.gitignore
ovpn_portal/static/README.md
ovpn_portal/static/dist/assets/main.css
ovpn_portal/static/dist/favicon.ico
ovpn_portal/static/dist/images/openvpn_logo.png
ovpn_portal/static/dist/index.html
ovpn_portal/static/dist/index.js
ovpn_portal/static/eslint.config.js
ovpn_portal/static/index.html
ovpn_portal/static/package-lock.json
ovpn_portal/static/package.json
ovpn_portal/static/public/favicon.ico
ovpn_portal/static/public/images/openvpn_logo.png
ovpn_portal/static/src/App.css
ovpn_portal/static/src/App.jsx
ovpn_portal/static/src/components/AuthStatus/index.jsx
ovpn_portal/static/src/components/CommandBlock/index.jsx
ovpn_portal/static/src/components/ConnectionDiagnostics/index.jsx
ovpn_portal/static/src/components/DownloadConfig/index.jsx
ovpn_portal/static/src/components/DownloadLink/index.jsx
ovpn_portal/static/src/components/Drawer/index.jsx
ovpn_portal/static/src/components/DrawerFooter/index.jsx
ovpn_portal/static/src/components/InstructionCard/index.jsx
ovpn_portal/static/src/components/Instructions/index.jsx
ovpn_portal/static/src/components/Logo/index.jsx
ovpn_portal/static/src/components/NetworkMetrics/index.jsx
ovpn_portal/static/src/components/StatusIndicator/index.jsx
ovpn_portal/static/src/components/VPNStatus/index.jsx
ovpn_portal/static/src/context/AuthContext.jsx
ovpn_portal/static/src/hooks/useGoogleAuth.js
ovpn_portal/static/src/hooks/useServerStatus.js
ovpn_portal/static/src/hooks/useVpnStatus.js
ovpn_portal/static/src/index.css
ovpn_portal/static/src/main.jsx
ovpn_portal/static/src/services/api.js
gcp_ovpn_portal-0.4.7.dist-info/LICENSE
gcp_ovpn_portal-0.4.7.dist-info/METADATA
gcp_ovpn_portal-0.4.7.dist-info/WHEEL
gcp_ovpn_portal-0.4.7.dist-info/entry_points.txt
gcp_ovpn_portal-0.4.7.dist-info/RECORD
