Metadata-Version: 2.3
Name: gcp-ovpn-portal
Version: 0.4.7
Summary: A secure OpenVPN authentication portal with Google OAuth2
License: MIT
Keywords: vpn,openvpn,oauth,google-auth,flask
Author: Abigail Ranson
Author-email: abby@abbyranson.com
Requires-Python: >=3.8.1,<4.0
Classifier: Development Status :: 4 - Beta
Classifier: Environment :: Web Environment
Classifier: Framework :: Flask
Classifier: Intended Audience :: System Administrators
Classifier: License :: OSI Approved :: MIT License
Classifier: Operating System :: OS Independent
Classifier: Programming Language :: Python :: 3
Classifier: Programming Language :: Python :: 3.9
Classifier: Programming Language :: Python :: 3.10
Classifier: Programming Language :: Python :: 3.11
Classifier: Programming Language :: Python :: 3.12
Classifier: Programming Language :: Python :: 3.13
Classifier: Programming Language :: Python :: 3.8
Classifier: Topic :: Security
Classifier: Topic :: System :: Systems Administration
Requires-Dist: Flask (>=2.0.0,<3.0.0)
Requires-Dist: click (>=8.0.0,<9.0.0)
Requires-Dist: flask-cors (>=4.0.0,<5.0.0)
Requires-Dist: google-auth (>=2.0.0,<3.0.0)
Requires-Dist: gunicorn (>=21.0.0,<22.0.0)
Requires-Dist: honcho (>=1.1.0,<2.0.0)
Requires-Dist: python-dotenv (>=0.19.0,<0.20.0)
Requires-Dist: requests (>=2.31.0,<3.0.0)
Requires-Dist: tomli (>=2.0.1,<3.0.0)
Project-URL: Documentation, https://github.com/ranson21/ovpn-client-web#readme
Project-URL: Homepage, https://github.com/ranson21/ovpn-client-web
Project-URL: Repository, https://github.com/ranson21/ovpn-client-web
